hlint/__init__.py
hlint/lint.py
hlint-0.0.1.dist-info/DESCRIPTION.rst
hlint-0.0.1.dist-info/METADATA
hlint-0.0.1.dist-info/RECORD
hlint-0.0.1.dist-info/WHEEL
hlint-0.0.1.dist-info/metadata.json
hlint-0.0.1.dist-info/top_level.txt
