Metadata-Version: 2.0
Name: hlint
Version: 0.0.1
Summary: HTML 5 Linter using Mozilla validation services
Home-page: https://github.com/AndrewRPorter/hlint
Author: AndrewRPorter
Author-email: porter.r.andrew@gmail.com
License: MIT License
Requires-Dist: setuptools
